README.md
setup.py
./src/CMakeLists.txt
./src/binding
./src/cmake
./src/third_party
./src/binding/CMakeLists.txt
./src/binding/binding.cpp
./src/binding/declarations.hpp
./src/binding/effector.cpp
./src/binding/enums.cpp
./src/binding/errors.cpp
./src/binding/frame.cpp
./src/binding/interpolate.cpp
./src/binding/motion.cpp
./src/binding/optional_caster.hpp
./src/binding/ranges.cpp
./src/cmake/clang-format.cmake
./src/third_party/pybind11
./src/third_party/pybind11/CMakeLists.txt
./src/third_party/pybind11/CONTRIBUTING.md
./src/third_party/pybind11/ISSUE_TEMPLATE.md
./src/third_party/pybind11/LICENSE
./src/third_party/pybind11/MANIFEST.in
./src/third_party/pybind11/README.md
./src/third_party/pybind11/docs
./src/third_party/pybind11/include
./src/third_party/pybind11/pybind11
./src/third_party/pybind11/setup.cfg
./src/third_party/pybind11/setup.py
./src/third_party/pybind11/tests
./src/third_party/pybind11/tools
./src/third_party/pybind11/docs/Doxyfile
./src/third_party/pybind11/docs/Makefile
./src/third_party/pybind11/docs/_static
./src/third_party/pybind11/docs/advanced
./src/third_party/pybind11/docs/basics.rst
./src/third_party/pybind11/docs/benchmark.py
./src/third_party/pybind11/docs/benchmark.rst
./src/third_party/pybind11/docs/changelog.rst
./src/third_party/pybind11/docs/classes.rst
./src/third_party/pybind11/docs/compiling.rst
./src/third_party/pybind11/docs/conf.py
./src/third_party/pybind11/docs/faq.rst
./src/third_party/pybind11/docs/index.rst
./src/third_party/pybind11/docs/intro.rst
./src/third_party/pybind11/docs/limitations.rst
./src/third_party/pybind11/docs/pybind11-logo.png
./src/third_party/pybind11/docs/pybind11_vs_boost_python1.png
./src/third_party/pybind11/docs/pybind11_vs_boost_python1.svg
./src/third_party/pybind11/docs/pybind11_vs_boost_python2.png
./src/third_party/pybind11/docs/pybind11_vs_boost_python2.svg
./src/third_party/pybind11/docs/reference.rst
./src/third_party/pybind11/docs/release.rst
flom.egg-info/PKG-INFO
flom.egg-info/SOURCES.txt
flom.egg-info/dependency_links.txt
flom.egg-info/not-zip-safe
flom.egg-info/top_level.txt
