Metadata-Version: 2.1
Name: flom
Version: 0.4.2
Summary: flom: a library to handle keyframed motion of robots
Home-page: UNKNOWN
Author: coord.e
Author-email: me@coord-e.com
License: UNKNOWN
Platform: UNKNOWN
Classifier: Development Status :: 4 - Beta
Classifier: Intended Audience :: Developers
Classifier: License :: OSI Approved :: GNU General Public License v3 (GPLv3)
Classifier: Operating System :: POSIX
Classifier: Programming Language :: Python
Classifier: Programming Language :: C++
Classifier: Topic :: Software Development :: Libraries
Classifier: Topic :: Scientific/Engineering :: Visualization
Classifier: Topic :: Software Development :: Libraries :: Python Modules
